enkacard/enc_error.py
enkacard/encbanner.py
enkacard/enkatools.py
enkacard/src/assets/font/Genshin_Impact.ttf
enkacard/src/assets/font/GSEnochian.ttf
enkacard/src/generator/akasha_rank.py
enkacard/src/generator/one/artifact.py
enkacard/src/generator/one/background.py
enkacard/src/generator/one/constant.py
enkacard/src/generator/one/prop.py
enkacard/src/generator/one/skill.py
enkacard/src/generator/one/stat.py
enkacard/src/generator/one/weapon.py
enkacard/src/generator/profile_teample_one.py
enkacard/src/generator/profile_teample_two.py
enkacard/src/generator/teample_one.py
enkacard/src/generator/teample_two.py
enkacard/src/generator/two/artifact.py
enkacard/src/generator/two/background.py
enkacard/src/generator/two/skill.py
enkacard/src/generator/two/stat.py
enkacard/src/modal/enkacardCread.py
enkacard/src/modal/enkaToolsModel.py
enkacard/src/pickle_cashe/data_characters.pkz
enkacard/src/pickle_cashe/data_characters.pkz~
enkacard/src/utils/affixes.py
enkacard/src/utils/diagram.py
enkacard/src/utils/git.py
enkacard/src/utils/options.py
enkacard/src/utils/pickle_cashe.py
enkacard/src/utils/pill.py
enkacard/src/utils/translation.py
enkacard-3.3.9.dist-info/METADATA
enkacard-3.3.9.dist-info/WHEEL
enkacard-3.3.9.dist-info/RECORD
