Metadata-Version: 2.1
Name: enkacard
Version: 3.3.9
Summary: An asynchronous module and API that allows you to connect to your bot the generation of Genshin character cards from the Enka.Network website.
Home-page: https://github.com/DEViantUA/EnkaCard
Author: None
Requires-Python: >=3.10,<4.0
Classifier: Programming Language :: Python :: 3
Classifier: Programming Language :: Python :: 3.10
Classifier: Programming Language :: Python :: 3.11
Requires-Dist: Pillow
Requires-Dist: aiofiles
Requires-Dist: asyncache
Requires-Dist: cachetools
Requires-Dist: enkanetworkv2.py
Requires-Dist: matplotlib
Requires-Dist: more-itertools
Requires-Dist: numpy
Requires-Dist: pydantic
Requires-Dist: python-magic (>=0.4.27,<0.5.0) ; sys_platform == "windows"
Requires-Dist: python-magic-bin (>=0.4.14,<0.5.0) ; sys_platform == "windows"
Project-URL: Repository, https://github.com/DEViantUA/EnkaCard
